adder/pipelined_adder.v
module pipelined_adder #(parameter N=8, STAGES=2) (
    input clk,
    input reset,
    input [N-1:0] A,
    input [N-1:0] B,
    input Cin,
    output reg [N-1:0] Sum,
    output reg Cout
);
   
    reg [N/2-1:0] sum_low;
    reg carry_mid;

     reg [N/2-1:0] sum_high;
    reg carry_out;

    always @(posedge clk or posedge reset) begin
        if(reset) begin
            sum_low <= 0;
            carry_mid <= 0;
            sum_high <= 0;
            carry_out <= 0;
            Sum <= 0;
            Cout <= 0;
        end else begin
            {carry_mid, sum_low} <= A[N/2-1:0] + B[N/2-1:0] + Cin;
            {carry_out, sum_high} <= A[N-1:N/2] + B[N-1:N/2] + carry_mid;
            Sum <= {sum_high, sum_low};
            Cout <= carry_out;
        end
    end
endmodule

adder/testbench/pipelined_adder_tb.v
`timescale 1ns/1ps

module pipelined_adder_tb;
    parameter N = 8;
    reg clk, reset;
    reg [N-1:0] A, B;
    reg Cin;
    wire [N-1:0] Sum;
    wire Cout;

    pipelined_adder #(N, 2) uut (
        .clk(clk),
        .reset(reset),
        .A(A),
        .B(B),
        .Cin(Cin),
        .Sum(Sum),
        .Cout(Cout)
    );

    // Horloge
    initial clk = 0;
    always #5 clk = ~clk; // 100MHz

    // Fichier VCD pour GTKWave
    initial begin
        $dumpfile("pipelined_adder.vcd");
        $dumpvars(0, pipelined_adder_tb);
    end

    // Cas de test
    initial begin
        // Réinitialisation
        reset = 1;
        A = 0;
        B = 0;
        Cin = 0;
        #10;

        reset = 0;

        // Cas 1 : 10 + 20
        A = 8'd10;
        B = 8'd20;
        Cin = 0;
        #10;

        // Cas 2 : 255 + 1 avec retenue
        A = 8'd255;
        B = 8'd1;
        Cin = 1;
        #10;

        // Cas 3 : 128 + 128
        A = 8'd128;
        B = 8'd128;
        Cin = 0;
        #10;

        // Cas 4 : 100 + 55
        A = 8'd100;
        B = 8'd55;
        Cin = 0;
        #10;

        // Cas 5 : 127 + 1 + Cin
        A = 8'd127;
        B = 8'd1;
        Cin = 1;
        #10;

        // Délai pour que les données sortent
        #30;

        // Affichage final (console)
        $display("Dernier résultat : A = %d, B = %d, Cin = %b => Sum = %d, Cout = %b",
                 A, B, Cin, Sum, Cout);

        $finish;
    end
endmodule

adder/pipelined_adder.vcd
$date
	Tue Jun 17 04:44:01 2025
$end
$version
	Icarus Verilog
$end
$timescale
	1ps
$end
$scope module pipelined_adder_tb $end
$var wire 8 ! Sum [7:0] $end
$var wire 1 " Cout $end
$var parameter 32 # N $end
$var reg 8 $ A [7:0] $end
$var reg 8 % B [7:0] $end
$var reg 1 & Cin $end
$var reg 1 ' clk $end
$var reg 1 ( reset $end
$scope module uut $end
$var wire 8 ) A [7:0] $end
$var wire 8 * B [7:0] $end
$var wire 1 & Cin $end
$var wire 1 ' clk $end
$var wire 1 ( reset $end
$var parameter 32 + N $end
$var parameter 32 , STAGES $end
$var reg 1 " Cout $end
$var reg 8 - Sum [7:0] $end
$var reg 1 . carry_mid $end
$var reg 1 / carry_out $end
$var reg 4 0 sum_high [3:0] $end
$var reg 4 1 sum_low [3:0] $end
$upscope $end
$upscope $end
$enddefinitions $end
$comment Show the parameter values. $end
$dumpall
b10 ,
b1000 +
b1000 #
$end
#0
$dumpvars
b0 1
b0 0
0/
0.
b0 -
b0 *
b0 )
1(
0'
0&
b0 %
b0 $
0"
b0 !
$end
#5000
1'
#10000
0'
b10100 %
b10100 *
b1010 $
b1010 )
0(
#15000
b1 0
b1110 1
1'
#20000
0'
1&
b1 %
b1 *
b11111111 $
b11111111 )
#25000
b11110 !
b11110 -
b1111 0
1.
b1 1
1'
#30000
0'
0&
b10000000 %
b10000000 *
b10000000 $
b10000000 )
#35000
b11110001 !
b11110001 -
1/
b1 0
0.
b0 1
1'
#40000
0'
b110111 %
b110111 *
b1100100 $
b1100100 )
#45000
1"
b10000 !
b10000 -
0/
b1001 0
b1011 1
1'
#50000
0'
1&
b1 %
b1 *
b1111111 $
b1111111 )
#55000
0"
b10011011 !
b10011011 -
b111 0
1.
b1 1
1'
#60000
0'
#65000
b1110001 !
b1110001 -
b1000 0
1'
#70000
0'
#75000
b10000001 !
b10000001 -
1'
